unimport/__init__.py
unimport/__main__.py
unimport/color.py
unimport/config.py
unimport/constants.py
unimport/enums.py
unimport/exceptions.py
unimport/main.py
unimport/meta.py
unimport/py.typed
unimport/refactor.py
unimport/statement.py
unimport/typing.py
unimport/utils.py
unimport/analyzers/__init__.py
unimport/analyzers/decarators.py
unimport/analyzers/import_statement.py
unimport/analyzers/importable.py
unimport/analyzers/main.py
unimport/analyzers/name.py
unimport/analyzers/utils.py
unimport/commands/__init__.py
unimport/commands/check.py
unimport/commands/diff.py
unimport/commands/options.py
unimport/commands/parser.py
unimport/commands/permission.py
unimport/commands/remove.py
unimport-1.3.0.dist-info/licenses/LICENSE
unimport-1.3.0.dist-info/METADATA
unimport-1.3.0.dist-info/WHEEL
unimport-1.3.0.dist-info/entry_points.txt
unimport-1.3.0.dist-info/top_level.txt
unimport-1.3.0.dist-info/zip-safe
unimport-1.3.0.dist-info/RECORD
