Metadata-Version: 2.4
Name: unimport
Version: 1.3.0
Summary: The ultimate linter and formatter for removing unused import statements in your code.
Author-email: Hakan Çelik <hakancelikdev@gmail.com>
License: MIT
Project-URL: Documentation, https://unimport.hakancelik.dev/
Project-URL: Issues, https://github.com/hakancelikdev/unimport/issues/
Project-URL: Changelog, https://unimport.hakancelik.dev/1.3.0/CHANGELOG/
Keywords: unused,import
Classifier: Development Status :: 5 - Production/Stable
Classifier: License :: OSI Approved :: MIT License
Classifier: Operating System :: OS Independent
Classifier: Programming Language :: Python
Classifier: Programming Language :: Python :: 3
Classifier: Programming Language :: Python :: 3 :: Only
Classifier: Programming Language :: Python :: 3.9
Classifier: Programming Language :: Python :: 3.10
Classifier: Programming Language :: Python :: 3.11
Classifier: Programming Language :: Python :: 3.12
Classifier: Programming Language :: Python :: 3.13
Classifier: Programming Language :: Python :: Implementation :: CPython
Classifier: Environment :: Console
Classifier: Topic :: Software Development :: Libraries :: Python Modules
Requires-Python: <3.14,>=3.9
License-File: LICENSE
Requires-Dist: libcst<=1.8.2,>=0.4.10; python_version >= "3.11"
Requires-Dist: libcst<=1.8.2,>=0.3.7; python_version == "3.10"
Requires-Dist: libcst<=1.8.2,>=0.3.7; python_version == "3.9"
Requires-Dist: pathspec<1,>=0.10.1
Requires-Dist: toml<1,>=0.9.0
Provides-Extra: docs
Requires-Dist: mkdocs==1.6.1; extra == "docs"
Requires-Dist: mkdocs-material==9.6.16; extra == "docs"
Requires-Dist: mkdocs-markdownextradata-plugin==0.2.6; extra == "docs"
Requires-Dist: mkdocs-minify-plugin==0.8.0; extra == "docs"
Requires-Dist: mkdocs-git-revision-date-localized-plugin==1.4.7; extra == "docs"
Requires-Dist: mike==2.1.3; extra == "docs"
Provides-Extra: test
Requires-Dist: pytest==8.4.1; extra == "test"
Requires-Dist: pytest-cov==6.2.1; extra == "test"
Requires-Dist: semantic-version==2.10.0; extra == "test"
Dynamic: license-file
